streamlit_allauth/__init__.py
streamlit_allauth/localstorage.py
streamlit_allauth-0.1.0.dist-info/METADATA
streamlit_allauth-0.1.0.dist-info/WHEEL
streamlit_allauth-0.1.0.dist-info/RECORD
