Metadata-Version: 2.1
Name: streamlit-allauth
Version: 0.1.0
Summary: 
Author: Alexandre Meline
Author-email: alexandre.meline.dev@gmail.com
Requires-Python: >=3.10,<4.0
Classifier: Programming Language :: Python :: 3
Classifier: Programming Language :: Python :: 3.10
Classifier: Programming Language :: Python :: 3.11
Classifier: Programming Language :: Python :: 3.12
Requires-Dist: streamlit (>=1.33.0,<2.0.0)
